{
  "generator-jhipster": {
    "promptValues": {
      "packageName": "br.com.jhisolution.apex"
    },
    "jhipsterVersion": "5.1.0",
    "applicationType": "monolith",
    "baseName": "apex",
    "packageName": "br.com.jhisolution.apex",
    "packageFolder": "br/com/jhisolution/apex",
    "serverPort": "8080",
    "authenticationType": "jwt",
    "cacheProvider": "ehcache",
    "enableHibernateCache": false,
    "websocket": false,
    "databaseType": "sql",
    "devDatabaseType": "mariadb",
    "prodDatabaseType": "mariadb",
    "searchEngine": false,
    "messageBroker": false,
    "serviceDiscoveryType": false,
    "buildTool": "maven",
    "enableSwaggerCodegen": false,
    "jwtSecretKey": "0976f1e3fb38abdf048d133933b775dd6bd25f52",
    "clientFramework": "angularX",
    "useSass": false,
    "clientPackageManager": "yarn",
    "testFrameworks": [],
    "jhiPrefix": "jhi",
    "enableTranslation": false
  }
}